LICENSE
README.md
setup.py
duwi_open_sdk/__init__.py
duwi_open_sdk/base_api.py
duwi_open_sdk/const.py
duwi_open_sdk/customer_client.py
duwi_open_sdk/device_control.py
duwi_open_sdk/device_scene_models.py
duwi_open_sdk/manager.py
duwi_open_sdk/sign.py
duwi_open_sdk/ws.py
duwi_open_sdk.egg-info/PKG-INFO
duwi_open_sdk.egg-info/SOURCES.txt
duwi_open_sdk.egg-info/dependency_links.txt
duwi_open_sdk.egg-info/top_level.txt