Metadata-Version: 2.1
Name: duwi_open_sdk
Version: 0.2.5
Summary: sdk for duwi third platform
Home-page: https://github.com/duwi2024/homeassistant-sdk
Author: ledgerbiggg
Author-email: duwitech@163.com
License: MIT
Keywords: python,duwi,sdk,third,platform
Classifier: Development Status :: 4 - Beta
Classifier: License :: OSI Approved :: MIT License
Classifier: Operating System :: OS Independent
Classifier: Topic :: Software Development
Classifier: Programming Language :: Python :: 3
Classifier: Programming Language :: Python :: 3.7
Classifier: Programming Language :: Python :: 3.8
Classifier: Programming Language :: Python :: 3.9
Classifier: Programming Language :: Python :: 3.10
Classifier: Programming Language :: Python :: Implementation :: PyPy
Requires-Python: >=3.7
License-File: LICENSE
